upload_eggest/__init__.py
upload_eggest-1.0.0.dist-info/METADATA
upload_eggest-1.0.0.dist-info/WHEEL
upload_eggest-1.0.0.dist-info/top_level.txt
upload_eggest-1.0.0.dist-info/RECORD
